mod3/mod3.v
module mod3(
	input clk,
	input rstb,
	input input_num,
	output res);

localparam S0 = 2'b00,
	S1 = 2'b01,
	S2 = 2'b10,
	S3 = 2'b11;

wire clk,input_num,rstb;
reg res,num;
reg [1:0] now_state,next_state;

always@(*)
begin
	case(now_state)
		S0:
		begin
			if(num)
				next_state = S1;
			else
				next_state = S0;
		end

		S1:
		begin
			if(num)
				next_state = S3;
			else
				next_state = S2;
		end

		S2: 
		begin
			if(num)
				next_state = S1;
			else
				next_state = S0;
		end

		S3:
		begin
			if(num)
				next_state = S1;
			else
				next_state = S3;
		end
		default:begin end
endcase
end

always@(posedge clk or negedge rstb)
begin
	if(!rstb)
	begin
		now_state <= S0;
		next_state <= S0;
		num <= 1'b0;
	end
	else
	begin
		num <= input_num;
		now_state <= next_state;
		//now_state <= (next_state << 1) % 3;
		if(now_state == S3)
			res = 1'b1;
		else
			res = 1'b0;
	end
end
endmodule

mod3/tb_mod3.v
`timescale 1ns/1ps
module mod3_tb;

reg clk;
reg input_num;
reg rstb;
wire res;

initial
begin
	clk = 1'b1;
	rstb = 1'b0;
	#50 rstb = ~rstb;
end

always
begin
	//input_num = {$random}%2;
	#50 clk = ~clk;
	//input_num = {$random}%2;
end

always@(posedge clk)
begin
	input_num = {$random}%2;
end


mod3 mod3_instance(
	.clk(clk),
	.rstb(rstb),
	.input_num(input_num),
	.res(res));

initial begin
	$dumpfile("mod3_tb.vcd");
	$dumpvars(0,mod3_tb);
end

initial #10000 $finish;

endmodule

mod3/mod3_tb.vcd
$date
	Thu Aug 22 22:59:58 2019
$end
$version
	Icarus Verilog
$end
$timescale
	1ps
$end
$scope module mod3_tb $end
$var wire 1 ! res $end
$var reg 1 " clk $end
$var reg 1 # input_num $end
$var reg 1 $ rstb $end
$scope module mod3_instance $end
$var wire 1 " clk $end
$var wire 1 # input_num $end
$var wire 1 $ rstb $end
$var reg 2 % next_state [1:0] $end
$var reg 2 & now_state [1:0] $end
$var reg 1 ' num $end
$var reg 1 ! res $end
$upscope $end
$upscope $end
$enddefinitions $end
#0
$dumpvars
0'
b0 &
b0 %
0$
x#
1"
x!
$end
#50000
0"
1$
#100000
0!
0#
1"
#150000
0"
#200000
b1 %
1'
1#
1"
#250000
0"
#300000
b11 %
b1 &
1"
#350000
0"
#400000
b1 %
b11 &
1"
#450000
0"
#500000
b11 %
b1 &
1!
1"
#550000
0"
#600000
b1 %
b11 &
0!
1"
#650000
0"
#700000
b11 %
b1 &
1!
1"
#750000
0"
#800000
b11 &
0'
0!
0#
1"
#850000
0"
#900000
b1 %
1'
1!
1#
1"
#950000
0"
#1000000
b11 %
b1 &
1"
#1050000
0"
#1100000
b11 &
0'
0!
0#
1"
#1150000
0"
#1200000
b1 %
1'
1!
1#
1"
#1250000
0"
#1300000
b11 %
b1 &
1"
#1350000
0"
#1400000
b11 &
0'
0!
0#
1"
#1450000
0"
#1500000
b1 %
1'
1!
1#
1"
#1550000
0"
#1600000
b10 %
b1 &
0'
0#
1"
#1650000
0"
#1700000
b1 %
b10 &
1'
0!
1#
1"
#1750000
0"
#1800000
b10 %
b1 &
0'
0#
1"
#1850000
0"
#1900000
b1 %
b10 &
1'
1#
1"
#1950000
0"
#2000000
b11 %
b1 &
1"
#2050000
0"
#2100000
b11 &
0'
0#
1"
#2150000
0"
#2200000
b1 %
1'
1!
1#
1"
#2250000
0"
#2300000
b10 %
b1 &
0'
0#
1"
#2350000
0"
#2400000
b0 %
b10 &
0!
1"
#2450000
0"
#2500000
b0 &
1"
#2550000
0"
#2600000
b1 %
1'
1#
1"
#2650000
0"
#2700000
b10 %
b1 &
0'
0#
1"
#2750000
0"
#2800000
b1 %
b10 &
1'
1#
1"
#2850000
0"
#2900000
b11 %
b1 &
1"
#2950000
0"
#3000000
b1 %
b11 &
1"
#3050000
0"
#3100000
b11 %
b1 &
1!
1"
#3150000
0"
#3200000
b11 &
0'
0!
0#
1"
#3250000
0"
#3300000
1!
1"
#3350000
0"
#3400000
1"
#3450000
0"
#3500000
1"
#3550000
0"
#3600000
b1 %
1'
1#
1"
#3650000
0"
#3700000
b10 %
b1 &
0'
0#
1"
#3750000
0"
#3800000
b1 %
b10 &
1'
0!
1#
1"
#3850000
0"
#3900000
b11 %
b1 &
1"
#3950000
0"
#4000000
b1 %
b11 &
1"
#4050000
0"
#4100000
b11 %
b1 &
1!
1"
#4150000
0"
#4200000
b1 %
b11 &
0!
1"
#4250000
0"
#4300000
b10 %
b1 &
0'
1!
0#
1"
#4350000
0"
#4400000
b0 %
b10 &
0!
1"
#4450000
0"
#4500000
b1 %
b0 &
1'
1#
1"
#4550000
0"
#4600000
b11 %
b1 &
1"
#4650000
0"
#4700000
b1 %
b11 &
1"
#4750000
0"
#4800000
b10 %
b1 &
0'
1!
0#
1"
#4850000
0"
#4900000
b0 %
b10 &
0!
1"
#4950000
0"
#5000000
b0 &
1"
#5050000
0"
#5100000
1"
#5150000
0"
#5200000
1"
#5250000
0"
#5300000
b1 %
1'
1#
1"
#5350000
0"
#5400000
b10 %
b1 &
0'
0#
1"
#5450000
0"
#5500000
b0 %
b10 &
1"
#5550000
0"
#5600000
b1 %
b0 &
1'
1#
1"
#5650000
0"
#5700000
b11 %
b1 &
1"
#5750000
0"
#5800000
b11 &
0'
0#
1"
#5850000
0"
#5900000
1!
1"
#5950000
0"
#6000000
1"
#6050000
0"
#6100000
1"
#6150000
0"
#6200000
1"
#6250000
0"
#6300000
b1 %
1'
1#
1"
#6350000
0"
#6400000
b11 %
b1 &
1"
#6450000
0"
#6500000
b1 %
b11 &
0!
1"
#6550000
0"
#6600000
b11 %
b1 &
1!
1"
#6650000
0"
#6700000
b1 %
b11 &
0!
1"
#6750000
0"
#6800000
b10 %
b1 &
0'
1!
0#
1"
#6850000
0"
#6900000
b0 %
b10 &
0!
1"
#6950000
0"
#7000000
b1 %
b0 &
1'
1#
1"
#7050000
0"
#7100000
b11 %
b1 &
1"
#7150000
0"
#7200000
b1 %
b11 &
1"
#7250000
0"
#7300000
b10 %
b1 &
0'
1!
0#
1"
#7350000
0"
#7400000
b0 %
b10 &
0!
1"
#7450000
0"
#7500000
b1 %
b0 &
1'
1#
1"
#7550000
0"
#7600000
b11 %
b1 &
1"
#7650000
0"
#7700000
b11 &
0'
0#
1"
#7750000
0"
#7800000
b1 %
1'
1!
1#
1"
#7850000
0"
#7900000
b11 %
b1 &
1"
#7950000
0"
#8000000
b11 &
0'
0!
0#
1"
#8050000
0"
#8100000
b1 %
1'
1!
1#
1"
#8150000
0"
#8200000
b11 %
b1 &
1"
#8250000
0"
#8300000
b1 %
b11 &
0!
1"
#8350000
0"
#8400000
b10 %
b1 &
0'
1!
0#
1"
#8450000
0"
#8500000
b1 %
b10 &
1'
0!
1#
1"
#8550000
0"
#8600000
b11 %
b1 &
1"
#8650000
0"
#8700000
b11 &
0'
0#
1"
#8750000
0"
#8800000
1!
1"
#8850000
0"
#8900000
1"
#8950000
0"
#9000000
1"
#9050000
0"
#9100000
b1 %
1'
1#
1"
#9150000
0"
#9200000
b11 %
b1 &
1"
#9250000
0"
#9300000
b11 &
0'
0!
0#
1"
#9350000
0"
#9400000
1!
1"
#9450000
0"
#9500000
b1 %
1'
1#
1"
#9550000
0"
#9600000
b11 %
b1 &
1"
#9650000
0"
#9700000
b1 %
b11 &
0!
1"
#9750000
0"
#9800000
b11 %
b1 &
1!
1"
#9850000
0"
#9900000
b1 %
b11 &
0!
1"
#9950000
0"
#10000000
b11 %
b1 &
1!
1"
