add_machine/add.v
module add(
	input clk,
	input [3:0] add_a,
	input [3:0] add_b,
	output [4:0] add_res);

	wire [3:0] add_a,add_b;
	reg [4:0] add_res;

	wire c_1;
	wire c_2;
	wire c_3;
	wire c_4;

	assign c_1 = add_a[0] & add_b[0];
	assign c_2 = (add_a[1] & add_b[1]) | ((add_a[1] ^ add_b[1]) & c_1);
	assign c_3 = (add_a[2] & add_b[2]) | ((add_a[2] ^ add_b[2]) & c_2);
	assign c_4 = (add_a[3] & add_b[3]) | ((add_a[3] ^ add_b[3]) & c_3);

	always@(posedge clk)
	begin
		add_res[0] <= add_a[0] ^ add_b[0];
		//c_1 <= add_a[0] & add_b[0];
		add_res[1] <= add_a[1] ^ add_b[1] ^ c_1;
		//c_2 <= (add_a[1] & add_b[1]) | ((add_a[1] ^ add_b[1]) & c_1);
		add_res[2] <= add_a[2] ^ add_b[2] ^ c_2;
		//c_3 <= (add_a[2] & add_b[2]) | ((add_a[2] ^ add_b[2]) & c_2);
		add_res[3] <= add_a[3] ^ add_b[3] ^ c_3;
		//c_4 <= (add_a[3] & add_b[3]) | ((add_a[3] ^ add_b[3]) & c_3);
		add_res[4] <= c_4;
	end

	endmodule

add_machine/tb_add.v
`timescale 1ns/1ps
module add_tb; 

reg clk;
reg [3:0] a;
reg [3:0] b;
wire [4:0] add_res;

initial
begin 
a = 3'b101;
b = 3'b011;
clk = 1'b1;
end   

always
begin
	#50 clk = ~clk;
	//a = {$random}%16;
	//b = {$random}%16;
end

always@(negedge clk)
begin
	a = {$random}%16;
	b = {$random}%16;
end

add add_instance( 
.clk(clk),
.add_a(a),
.add_b(b),
.add_res(add_res)
); 

initial begin 
$dumpfile("tb_add.vcd"); 
$dumpvars(0, add_tb); 
end 

initial #10000 $finish;

endmodule

add_machine/tb_add.vcd
$date
	Tue Aug 20 16:53:43 2019
$end
$version
	Icarus Verilog
$end
$timescale
	1ps
$end
$scope module add_tb $end
$var wire 5 ! add_res [4:0] $end
$var reg 4 " a [3:0] $end
$var reg 4 # b [3:0] $end
$var reg 1 $ clk $end
$scope module add_instance $end
$var wire 4 % add_a [3:0] $end
$var wire 4 & add_b [3:0] $end
$var wire 1 ' c_1 $end
$var wire 1 ( c_2 $end
$var wire 1 ) c_3 $end
$var wire 1 * c_4 $end
$var wire 1 $ clk $end
$var reg 5 + add_res [4:0] $end
$upscope $end
$upscope $end
$enddefinitions $end
#0
$dumpvars
bx0 +
0*
1)
1(
1'
b11 &
b101 %
1$
b11 #
b101 "
bx0 !
$end
#50000
0)
0(
0'
b1 #
b1 &
b100 "
b100 %
0$
#100000
b101 !
b101 +
1$
#150000
1(
1'
b11 #
b11 &
b1001 "
b1001 %
0$
#200000
b1100 !
b1100 +
1$
#250000
0(
1*
1)
b1101 #
b1101 &
b1101 "
b1101 %
0$
#300000
b11010 !
b11010 +
1$
#350000
0)
0*
0'
b10 #
b10 &
b101 "
b101 %
0$
#400000
b111 !
b111 +
1$
#450000
1'
b1101 #
b1101 &
b1 "
b1 %
0$
#500000
b1110 !
b1110 +
1$
#550000
1*
1)
0'
b110 "
b110 %
0$
#600000
b10011 !
b10011 +
1$
#650000
b1100 #
b1100 &
b1101 "
b1101 %
0$
#700000
b11001 !
b11001 +
1$
#750000
0*
0)
b110 #
b110 &
b1001 "
b1001 %
0$
#800000
b1111 !
b1111 +
1$
#850000
b1010 #
b1010 &
b101 "
b101 %
0$
#900000
1$
#950000
1(
1)
1'
b111 #
b111 &
0$
#1000000
b1100 !
b1100 +
1$
#1050000
1*
0'
b1111 #
b1111 &
b10 "
b10 %
0$
#1100000
b10001 !
b10001 +
1$
#1150000
b1110 #
b1110 &
0$
#1200000
b10000 !
b10000 +
1$
#1250000
0*
0)
0(
b101 #
b101 &
b1000 "
b1000 %
0$
#1300000
b1101 !
b1101 +
1$
#1350000
1*
1)
b1101 #
b1101 &
b1100 "
b1100 %
0$
#1400000
b11001 !
b11001 +
1$
#1450000
1'
b101 #
b101 &
b1101 "
b1101 %
0$
#1500000
b10010 !
b10010 +
1$
#1550000
0*
1(
0)
0'
b1010 #
b1010 &
b11 "
b11 %
0$
#1600000
b1101 !
b1101 +
1$
#1650000
0(
b0 #
b0 &
b0 "
b0 %
0$
#1700000
b0 !
b0 +
1$
#1750000
1*
b1101 #
b1101 &
b1010 "
b1010 %
0$
#1800000
b10111 !
b10111 +
1$
#1850000
1)
1(
0*
b11 #
b11 &
b110 "
b110 %
0$
#1900000
b1001 !
b1001 +
1$
#1950000
1*
1'
b1101 "
b1101 %
0$
#2000000
b10000 !
b10000 +
1$
#2050000
b101 #
b101 &
b1011 "
b1011 %
0$
#2100000
1$
#2150000
0'
b1110 #
b1110 &
b10 "
b10 %
0$
#2200000
1$
#2250000
1'
b1111 #
b1111 &
b1101 "
b1101 %
0$
#2300000
b11100 !
b11100 +
1$
#2350000
0*
0)
0'
b1010 #
b1010 &
b11 "
b11 %
0$
#2400000
b1101 !
b1101 +
1$
#2450000
0)
0(
1*
b1100 #
b1100 &
b1010 "
b1010 %
0$
#2500000
b10110 !
b10110 +
1$
#2550000
1(
0*
b1010 #
b1010 &
b10 "
b10 %
0$
#2600000
b1100 !
b1100 +
1$
#2650000
0(
b1000 #
b1000 &
b1 "
b1 %
0$
#2700000
b1001 !
b1001 +
1$
#2750000
1*
b1001 #
b1001 &
b1000 "
b1000 %
0$
#2800000
b10001 !
b10001 +
1$
#2850000
1)
1*
1(
b110 #
b110 &
b1011 "
b1011 %
0$
#2900000
1$
#2950000
b1110 #
b1110 &
b110 "
b110 %
0$
#3000000
b10100 !
b10100 +
1$
#3050000
0)
0(
b1010 #
b1010 &
b1100 "
b1100 %
0$
#3100000
b10110 !
b10110 +
1$
#3150000
1(
0*
1'
b1 #
b1 &
b1011 "
b1011 %
0$
#3200000
b1100 !
b1100 +
1$
#3250000
1*
1)
b1111 #
b1111 &
b101 "
b101 %
0$
#3300000
b10100 !
b10100 +
1$
#3350000
0)
0'
b1010 #
b1010 &
b1011 "
b1011 %
0$
#3400000
b10101 !
b10101 +
1$
#3450000
0(
1)
b101 #
b101 &
b1110 "
b1110 %
0$
#3500000
b10011 !
b10011 +
1$
#3550000
0*
0)
1'
b1001 #
b1001 &
b1 "
b1 %
0$
#3600000
b1010 !
b1010 +
1$
#3650000
0'
b1100 #
b1100 &
b10 "
b10 %
0$
#3700000
b1110 !
b1110 +
1$
#3750000
1(
1)
1*
1'
b1111 #
b1111 &
b1111 "
b1111 %
0$
#3800000
b11110 !
b11110 +
1$
#3850000
0*
0)
0(
0'
b111 #
b111 &
b1000 "
b1000 %
0$
#3900000
b1111 !
b1111 +
1$
#3950000
1*
1)
b1100 #
b1100 &
b1111 "
b1111 %
0$
#4000000
b11011 !
b11011 +
1$
#4050000
1(
0)
1'
b1001 #
b1001 &
b1011 "
b1011 %
0$
#4100000
b10100 !
b10100 +
1$
#4150000
0(
0*
0'
b0 #
b0 &
b1001 "
b1001 %
0$
#4200000
b1001 !
b1001 +
1$
#4250000
1)
1(
1'
b1 #
b1 &
b111 "
b111 %
0$
#4300000
b1000 !
b1000 +
1$
#4350000
1*
0(
0'
b1100 #
b1100 &
b110 "
b110 %
0$
#4400000
b10010 !
b10010 +
1$
#4450000
0*
0)
b1000 #
b1000 &
b10 "
b10 %
0$
#4500000
b1010 !
b1010 +
1$
#4550000
1*
1(
1)
1'
b1101 #
b1101 &
b111 "
b111 %
0$
#4600000
b10100 !
b10100 +
1$
#4650000
0'
b1110 #
b1110 &
b10 "
b10 %
0$
#4700000
b10000 !
b10000 +
1$
#4750000
0)
0(
1'
b1001 #
b1001 &
b1101 "
b1101 %
0$
#4800000
b10110 !
b10110 +
1$
#4850000
1)
1*
1(
b11 #
b11 &
b1111 "
b1111 %
0$
#4900000
b10010 !
b10010 +
1$
#4950000
0*
0)
0(
0'
b1000 #
b1000 &
b101 "
b101 %
0$
#5000000
b1101 !
b1101 +
1$
#5050000
1(
1*
1'
b1001 #
b1001 &
b1011 "
b1011 %
0$
#5100000
b10100 !
b10100 +
1$
#5150000
1)
0'
b1010 #
b1010 &
b1111 "
b1111 %
0$
#5200000
b11001 !
b11001 +
1$
#5250000
0*
0)
0(
b110 #
b110 &
b1000 "
b1000 %
0$
#5300000
b1110 !
b1110 +
1$
#5350000
1*
1)
b1100 #
b1100 &
b1110 "
b1110 %
0$
#5400000
b11010 !
b11010 +
1$
#5450000
1(
1*
1)
b110 #
b110 &
b1010 "
b1010 %
0$
#5500000
b10000 !
b10000 +
1$
#5550000
0)
0*
1'
b11 #
b11 &
b11 "
b11 %
0$
#5600000
b110 !
b110 +
1$
#5650000
1*
1)
b1111 "
b1111 %
0$
#5700000
b10010 !
b10010 +
1$
#5750000
0(
0'
b100 #
b100 &
0$
#5800000
b10011 !
b10011 +
1$
#5850000
1*
1(
1)
1'
b1011 #
b1011 &
b111 "
b111 %
0$
#5900000
b10010 !
b10010 +
1$
#5950000
0'
b1010 #
b1010 &
b110 "
b110 %
0$
#6000000
b10000 !
b10000 +
1$
#6050000
0)
0(
1'
b1101 #
b1101 &
b1001 "
b1001 %
0$
#6100000
b10110 !
b10110 +
1$
#6150000
0*
0'
b101 #
b101 &
b1010 "
b1010 %
0$
#6200000
b1111 !
b1111 +
1$
#6250000
1*
1(
1)
1'
b1111 #
b1111 &
b101 "
b101 %
0$
#6300000
b10100 !
b10100 +
1$
#6350000
0*
0)
0(
0'
b100 #
b100 &
b1001 "
b1001 %
0$
#6400000
b1101 !
b1101 +
1$
#6450000
b1010 #
b1010 &
b0 "
b0 %
0$
#6500000
b1010 !
b1010 +
1$
#6550000
1)
1(
1*
b1110 #
b1110 &
b1011 "
b1011 %
0$
#6600000
b11001 !
b11001 +
1$
#6650000
0)
0(
b1010 #
b1010 &
b1100 "
b1100 %
0$
#6700000
b10110 !
b10110 +
1$
#6750000
1)
1(
1*
1'
b11 #
b11 &
b1101 "
b1101 %
0$
#6800000
b10000 !
b10000 +
1$
#6850000
0'
b1110 #
b1110 &
b110 "
b110 %
0$
#6900000
b10100 !
b10100 +
1$
#6950000
b1010 #
b1010 &
b111 "
b111 %
0$
#7000000
b10001 !
b10001 +
1$
#7050000
0*
0)
0(
b1000 #
b1000 &
b110 "
b110 %
0$
#7100000
b1110 !
b1110 +
1$
#7150000
1*
b1001 "
b1001 %
0$
#7200000
b10001 !
b10001 +
1$
#7250000
0*
b11 #
b11 &
b100 "
b100 %
0$
#7300000
b111 !
b111 +
1$
#7350000
b1001 #
b1001 &
0$
#7400000
b1101 !
b1101 +
1$
#7450000
1)
1(
1*
1'
b1101 #
b1101 &
b1011 "
b1011 %
0$
#7500000
b11000 !
b11000 +
1$
#7550000
0)
0(
b1001 "
b1001 %
0$
#7600000
b10110 !
b10110 +
1$
#7650000
1)
1(
1*
0'
b1010 #
b1010 &
b110 "
b110 %
0$
#7700000
b10000 !
b10000 +
1$
#7750000
0*
0(
b101 #
b101 &
0$
#7800000
b1011 !
b1011 +
1$
#7850000
b100 #
b100 &
0$
#7900000
b1010 !
b1010 +
1$
#7950000
1*
1(
1)
1'
b1001 #
b1001 &
b111 "
b111 %
0$
#8000000
b10000 !
b10000 +
1$
#8050000
0*
0)
0(
0'
b1000 #
b1000 &
b100 "
b100 %
0$
#8100000
b1100 !
b1100 +
1$
#8150000
1*
b1101 #
b1101 &
b1000 "
b1000 %
0$
#8200000
b10101 !
b10101 +
1$
#8250000
1(
1)
1*
b1110 #
b1110 &
b111 "
b111 %
0$
#8300000
1$
#8350000
0)
0(
b1100 #
b1100 &
b1000 "
b1000 %
0$
#8400000
b10100 !
b10100 +
1$
#8450000
1'
b1001 #
b1001 &
b1101 "
b1101 %
0$
#8500000
b10110 !
b10110 +
1$
#8550000
1)
1*
0'
b110 #
b110 &
b1100 "
b1100 %
0$
#8600000
b10010 !
b10010 +
1$
#8650000
0)
b1101 #
b1101 &
b1010 "
b1010 %
0$
#8700000
b10111 !
b10111 +
1$
#8750000
0*
b0 #
b0 &
b110 "
b110 %
0$
#8800000
b110 !
b110 +
1$
#8850000
1(
b1010 #
b1010 &
b11 "
b11 %
0$
#8900000
b1101 !
b1101 +
1$
#8950000
1)
1*
b1110 "
b1110 %
0$
#9000000
b11000 !
b11000 +
1$
#9050000
0*
0)
0(
b101 "
b101 %
0$
#9100000
b1111 !
b1111 +
1$
#9150000
1*
1)
1(
1'
b111 #
b111 &
b1001 "
b1001 %
0$
#9200000
b10000 !
b10000 +
1$
#9250000
0)
0(
0*
0'
b0 #
b0 &
b110 "
b110 %
0$
#9300000
b110 !
b110 +
1$
#9350000
1(
1)
b110 #
b110 &
0$
#9400000
b1100 !
b1100 +
1$
#9450000
0(
1*
b1100 #
b1100 &
b1101 "
b1101 %
0$
#9500000
b11001 !
b11001 +
1$
#9550000
0*
0)
b1000 #
b1000 &
b110 "
b110 %
0$
#9600000
b1110 !
b1110 +
1$
#9650000
1)
1(
1*
b1011 #
b1011 &
b1110 "
b1110 %
0$
#9700000
b11001 !
b11001 +
1$
#9750000
1'
b1001 #
b1001 &
b1111 "
b1111 %
0$
#9800000
b11000 !
b11000 +
1$
#9850000
0*
0(
0)
0'
b1 #
b1 &
b1010 "
b1010 %
0$
#9900000
b1011 !
b1011 +
1$
#9950000
1)
1(
1'
b111 "
b111 %
0$
#10000000
b1000 !
b1000 +
1$
